MultiScaleDeformableAttention.cp38-win_amd64.pyd
functions/__init__.py
functions/ms_deform_attn_func.py
modules/__init__.py
modules/ms_deform_attn.py
MultiScaleDeformableAttention_Linux-1.0.dist-info/METADATA
MultiScaleDeformableAttention_Linux-1.0.dist-info/WHEEL
MultiScaleDeformableAttention_Linux-1.0.dist-info/top_level.txt
MultiScaleDeformableAttention_Linux-1.0.dist-info/RECORD
