Metadata-Version: 2.1
Name: MultiScaleDeformableAttention-Linux
Version: 1.0
Summary: PyTorch Wrapper for CUDA Functions of Multi-Scale Deformable Attention
Home-page: https://github.com/fundamentalvision/Deformable-DETR
Author: Weijie Su
